MANIFEST.in
README.md
setup.cfg
setup.py
version.txt
bash-autocompletion/lutin
bin/lutin
lutin/__init__.py
lutin/builder.py
lutin/depend.py
lutin/env.py
lutin/heritage.py
lutin/host.py
lutin/image.py
lutin/license.py
lutin/macro.py
lutin/module.py
lutin/multiprocess.py
lutin/system.py
lutin/target.py
lutin/tools.py
lutin/zip.py
lutin.egg-info/PKG-INFO
lutin.egg-info/SOURCES.txt
lutin.egg-info/dependency_links.txt
lutin.egg-info/not-zip-safe
lutin.egg-info/requires.txt
lutin.egg-info/top_level.txt
lutin/z_builder/__init__.py
lutin/z_builder/lutinBuilder_binary.py
lutin/z_builder/lutinBuilder_c.py
lutin/z_builder/lutinBuilder_cpp.py
lutin/z_builder/lutinBuilder_jar.py
lutin/z_builder/lutinBuilder_java.py
lutin/z_builder/lutinBuilder_javah.py
lutin/z_builder/lutinBuilder_libraryDynamic.py
lutin/z_builder/lutinBuilder_libraryStatic.py
lutin/z_builder/lutinBuilder_m.py
lutin/z_builder/lutinBuilder_mm.py
lutin/z_builder/lutinBuilder_s.py
lutin/z_system/__init__.py
lutin/z_system/lutinSystem_Android_ADMOD.py
lutin/z_system/lutinSystem_Android_SDK.py
lutin/z_system/lutinSystem_Android_c.py
lutin/z_system/lutinSystem_Android_cxx.py
lutin/z_system/lutinSystem_Android_m.py
lutin/z_system/lutinSystem_Android_opengl.py
lutin/z_system/lutinSystem_Android_pthread.py
lutin/z_system/lutinSystem_Android_z.py
lutin/z_system/lutinSystem_IOs_CoreAudio.py
lutin/z_system/lutinSystem_IOs_CoreGraphics.py
lutin/z_system/lutinSystem_IOs_Foundation.py
lutin/z_system/lutinSystem_IOs_GLKit.py
lutin/z_system/lutinSystem_IOs_QuartzCore.py
lutin/z_system/lutinSystem_IOs_UIKit.py
lutin/z_system/lutinSystem_IOs_c.py
lutin/z_system/lutinSystem_IOs_cxx.py
lutin/z_system/lutinSystem_IOs_m.py
lutin/z_system/lutinSystem_IOs_opengl.py
lutin/z_system/lutinSystem_IOs_pthread.py
lutin/z_system/lutinSystem_Linux_SDL.py
lutin/z_system/lutinSystem_Linux_X11.py
lutin/z_system/lutinSystem_Linux_alsa.py
lutin/z_system/lutinSystem_Linux_arpa.py
lutin/z_system/lutinSystem_Linux_boost.py
lutin/z_system/lutinSystem_Linux_c.py
lutin/z_system/lutinSystem_Linux_cxx.py
lutin/z_system/lutinSystem_Linux_egl.py
lutin/z_system/lutinSystem_Linux_gles2.py
lutin/z_system/lutinSystem_Linux_jack.py
