Metadata-Version: 2.1
Name: lutin
Version: 2.7.1
Summary: Lutin generic builder (might replace makefile, CMake ...)
Home-page: http://github.com/HeeroYui/lutin
Author: Edouard DUPIN
Author-email: yui.heero@gmail.com
License: MPL-2
Keywords: builder c++ c android ios macos makefile cmake
Platform: UNKNOWN
Classifier: Development Status :: 5 - Production/Stable
Classifier: License :: OSI Approved :: Mozilla Public License 2.0 (MPL 2.0)
Classifier: Programming Language :: Python
Classifier: Topic :: Software Development :: Build Tools
